chemcharts/__init__.py
chemcharts/core/__init__.py
chemcharts/core/container/__init__.py
chemcharts/core/container/chemdata.py
chemcharts/core/container/embedding.py
chemcharts/core/container/fingerprint.py
chemcharts/core/container/smiles.py
chemcharts/core/functions/__init__.py
chemcharts/core/functions/binning.py
chemcharts/core/functions/clustering.py
chemcharts/core/functions/dimensional_reduction.py
chemcharts/core/functions/filtering.py
chemcharts/core/functions/io_functions.py
chemcharts/core/functions/tanimoto_similarity.py
chemcharts/core/plots/__init__.py
chemcharts/core/plots/base_plot.py
chemcharts/core/plots/contour_plot.py
chemcharts/core/plots/hexag_plot.py
chemcharts/core/plots/histogram_plot.py
chemcharts/core/plots/scatter_boxplot_plot.py
chemcharts/core/plots/scatter_interactive_mol_plot.py
chemcharts/core/plots/scatter_interactive_plot.py
chemcharts/core/plots/scatter_static_plot.py
chemcharts/core/plots/trisurf_interactive_plot.py
chemcharts/core/plots/trisurf_static_plot.py
chemcharts/core/utils/__init__.py
chemcharts/core/utils/colour_functions.py
chemcharts/core/utils/enums.py
chemcharts/core/utils/files_paths.py
chemcharts/core/utils/print_dataframe.py
chemcharts/core/utils/value_functions.py
chemcharts/scripts/chemcharts_cli.py
chemcharts/scripts/chemcharts_json.py
chemcharts-0.9.0.dist-info/LICENSE
chemcharts-0.9.0.dist-info/METADATA
chemcharts-0.9.0.dist-info/WHEEL
chemcharts-0.9.0.dist-info/entry_points.txt
chemcharts-0.9.0.dist-info/top_level.txt
chemcharts-0.9.0.dist-info/RECORD
