Metadata-Version: 2.1
Name: chemcharts
Version: 0.9.0
Summary: ChemCharts: Chemical Space Visualizer
Home-page: https://github.com/SMargreitter/ChemCharts
Maintainer: Sophie Margreitter, Christian Margreitter
Requires-Python: >=3.8
License-File: LICENSE
Requires-Dist: dill
Requires-Dist: plotly >=5.1.0
Requires-Dist: rdkit >=2022.9.5
Requires-Dist: seaborn >=0.11
Requires-Dist: molplotly
Requires-Dist: ffmpeg-python >=0.2.0
Requires-Dist: scikit-learn >=0.24
Requires-Dist: umap-learn
Requires-Dist: kaleido
